<suitelet scriptid="customscript_jj_sl_employee_commission">
  <description></description>
  <isinactive>F</isinactive>
  <name>JJ SL Employee Commission</name>
  <notifyadmins>F</notifyadmins>
  <notifyemails></notifyemails>
  <notifyowner>T</notifyowner>
  <notifyuser>F</notifyuser>
  <scriptfile>[/SuiteScripts/JobinandJismi/RAF-3-Assessment/jj_sl_Employee Commission.js]</scriptfile>
  <scriptdeployments>
    <scriptdeployment scriptid="customdeploy_jj_sl_employee_commission">
      <allemployees>F</allemployees>
      <allpartners>F</allpartners>
      <allroles>F</allroles>
      <audslctrole></audslctrole>
      <eventtype></eventtype>
      <isdeployed>T</isdeployed>
      <isonline>F</isonline>
      <loglevel>DEBUG</loglevel>
      <runasrole></runasrole>
      <status>TESTING</status>
      <title>JJ SL Employee Commission</title>
    </scriptdeployment>
  </scriptdeployments>
</suitelet>